ezicon.py
ezicon-1.2.0.dist-info/METADATA
ezicon-1.2.0.dist-info/WHEEL
ezicon-1.2.0.dist-info/entry_points.txt
ezicon-1.2.0.dist-info/top_level.txt
ezicon-1.2.0.dist-info/RECORD
