Metadata-Version: 2.4
Name: ezicon
Version: 1.2.0
Summary: Create Windows Start Menu shortcuts for Python scripts instantly.
Author: gusta01010
Classifier: Programming Language :: Python :: 3
Classifier: Operating System :: Microsoft :: Windows
Requires-Dist: pywin32
Dynamic: author
Dynamic: classifier
Dynamic: description
Dynamic: description-content-type
Dynamic: requires-dist
Dynamic: summary
